spoon_cli/__init__.py
spoon_cli/__main__.py
spoon_cli/commands.py
spoon_cli/config/__init__.py
spoon_cli/config/base_tool.py
spoon_cli/config/errors.py
spoon_cli/config/manager.py
spoon_cli/config/mcp_manager.py
spoon_cli/config/migrate_config.py
spoon_cli/config/models.py
spoon_cli/config/tool_factory.py
spoon_cli/mcp/mcp_client_mixin.py
spoon_cli/mcp/mcp_tool.py
spoon_cli/mcp/mcp_tools_collection.py
spoon_cli-0.1.1.dist-info/METADATA
spoon_cli-0.1.1.dist-info/WHEEL
spoon_cli-0.1.1.dist-info/entry_points.txt
spoon_cli-0.1.1.dist-info/top_level.txt
spoon_cli-0.1.1.dist-info/RECORD
