Metadata-Version: 2.4
Name: spoon-cli
Version: 0.1.1
Summary: CLI for SpoonAI
Requires-Python: >=3.12
Requires-Dist: spoon-ai-sdk>=0.2.0
Requires-Dist: spoon-toolkits>=0.2.0
Requires-Dist: prompt_toolkit>=3.0.51
Requires-Dist: python-dotenv>=1.0.1
Requires-Dist: python-telegram-bot>=22.0
Requires-Dist: fastmcp>=2.12.0
Requires-Dist: pydantic>=2.10.4
Requires-Dist: websockets>=15.0.1
